{"time":{"updated":"Mar 11, 2024 00:51:19 UTC","updatedISO":"2024-03-11T00:51:19+00:00","updateduk":"Mar 11, 2024 at 00:51 GMT"},"disclaimer":"This data was produced from the CoinDesk Bitcoin Price Index (USD). Non-USD currency data converted using hourly conversion rate from openexchangerates.org","chartName":"Bitcoin","bpi":{"USD":{"code":"USD","symbol":"&#36;","rate":"67,762.972","description":"United States Dollar","rate_float":67762.9717},"GBP":{"code":"GBP","symbol":"&pound;","rate":"52,710.851","description":"British Pound Sterling","rate_float":52710.8506},"EUR":{"code":"EUR","symbol":"&euro;","rate":"61,924.446","description":"Euro","rate_float":61924.4463},"CNY":{"code":"CNY","symbol":"&yen;","rate":"483,910.086","description":"Chinese Yuan","rate_float":483910.0855}}}